itchat/__init__.py
itchat/config.py
itchat/content.py
itchat/core.py
itchat/log.py
itchat/returnvalues.py
itchat/utils.py
itchat/components/__init__.py
itchat/components/contact.py
itchat/components/hotreload.py
itchat/components/login.py
itchat/components/messages.py
itchat/components/register.py
itchat/storage/__init__.py
itchat/storage/messagequeue.py
itchat/storage/templates.py
itchat-1.3.9.dist-info/DESCRIPTION.rst
itchat-1.3.9.dist-info/METADATA
itchat-1.3.9.dist-info/RECORD
itchat-1.3.9.dist-info/WHEEL
itchat-1.3.9.dist-info/metadata.json
itchat-1.3.9.dist-info/top_level.txt
