Metadata-Version: 1.1
Name: itchat
Version: 1.3.9
Summary: A complete wechat personal account api
Home-page: https://github.com/littlecodersh/ItChat
Author: LittleCoder
Author-email: i7meavnktqegm1b@qq.com
License: MIT
Keywords: wechat itchat api robot weixin personal extend
Platform: UNKNOWN
Classifier: Development Status :: 3 - Alpha
Classifier: Intended Audience :: Developers
Classifier: Topic :: Software Development :: Libraries :: Python Modules
Classifier: License :: OSI Approved :: MIT License
Classifier: Programming Language :: Python :: 2
Classifier: Programming Language :: Python :: 2.6
Classifier: Programming Language :: Python :: 2.7
